Workbook

Sheet Sales Data
A1: Order_ID | B1: Date | C1: Region | D1: Salesperson | E1: Bike_Model | F1: Category | G1: Units_Sold | H1: Unit_Price | I1: Total_Revenue | J1: Cost_Per_Unit | K1: Total_Cost | L1: Profit
A2: ORD-1001 | B2: 2024-01-08 | C2: East | D2: Bob Smith | E2: Mountain Bike Pro | F2: Mountain | G2: 1 | H2: 850 | I2: =G2*H2 | J2: 510 | K2: =G2*J2 | L2: =I2-K2
A3: ORD-1002 | B3: 2024-01-14 | C3: North | D3: Eve Davis | E3: Road Racer X | F3: Road | G3: 2 | H3: 1200 | I3: =G3*H3 | J3: 720 | K3: =G3*J3 | L3: =I3-K3
A4: ORD-1003 | B4: 2024-01-08 | C4: North | D4: Bob Smith | E4: Mountain Bike Pro | F4: Mountain | G4: 1 | H4: 850 | I4: =G4*H4 | J4: 510 | K4: =G4*J4 | L4: =I4-K4
A5: ORD-1004 | B5: 2024-01-07 | C5: North | D5: Eve Davis | E5: Kids Rocket | F5: Kids | G5: 10 | H5: 180 | I5: =G5*H5 | J5: 108 | K5: =G5*J5 | L5: =I5-K5
A6: ORD-1005 | B6: 2024-01-15 | C6: West | D6: Bob Smith | E6: BMX Stunt | F6: BMX | G6: 9 | H6: 320 | I6: =G6*H6 | J6: 192 | K6: =G6*J6 | L6: =I6-K6
A7: ORD-1006 | B7: 2024-01-23 | C7: North | D7: Bob Smith | E7: Kids Rocket | F7: Kids | G7: 5 | H7: 180 | I7: =G7*H7 | J7: 108 | K7: =G7*J7 | L7: =I7-K7
A8: ORD-1007 | B8: 2024-01-07 | C8: East | D8: Bob Smith | E8: Electric eBike | F8: Electric | G8: 6 | H8: 2200 | I8: =G8*H8 | J8: 1320 | K8: =G8*J8 | L8: =I8-K8
A9: ORD-1008 | B9: 2024-01-13 | C9: North | D9: Alice Johnson | E9: Hybrid Commuter | F9: City | G9: 6 | H9: 650 | I9: =G9*H9 | J9: 390 | K9: =G9*J9 | L9: =I9-K9
A10: ORD-1009 | B10: 2024-01-09 | C10: East | D10: Eve Davis | E10: Mountain Bike Pro | F10: Mountain | G10: 6 | H10: 850 | I10: =G10*H10 | J10: 510 | K10: =G10*J10 | L10: =I10-K10
A11: ORD-1010 | B11: 2024-01-04 | C11: West | D11: Eve Davis | E11: Hybrid Commuter | F11: City | G11: 1 | H11: 650 | I11: =G11*H11 | J11: 390 | K11: =G11*J11 | L11: =I11-K11
A12: ORD-1011 | B12: 2024-01-28 | C12: East | D12: Eve Davis | E12: Electric eBike | F12: Electric | G12: 2 | H12: 2200 | I12: =G12*H12 | J12: 1320 | K12: =G12*J12 | L12: =I12-K12
A13: ORD-1012 | B13: 2024-01-02 | C13: South | D13: Alice Johnson | E13: City Cruiser | F13: City | G13: 10 | H13: 450 | I13: =G13*H13 | J13: 270 | K13: =G13*J13 | L13: =I13-K13
... A222: ORD-1221 | B222: 2024-12-03 | C222: West | D222: Bob Smith | E222: Mountain Bike Pro | F222: Mountain | G222: 3 | H222: 850 | I222: =G222*H222 | J222: 510 | K222: =G222*J222 | L222: =I222-K222

Sheet Summary
A1: Bike Sales Summary Dashboard
A3: KEY METRICS | D3: REVENUE BY CATEGORY
A4: Total Revenue | B4: =SUM('Sales Data'!I2:I222) | D4: Category | E4: Revenue
A5: Total Cost | B5: =SUM('Sales Data'!K2:K222) | D5: Mountain | E5: =SUMIF('Sales Data'!F2:F222,D5,'Sales Data'!I2:I222)
A6: Total Profit | B6: =SUM('Sales Data'!L2:L222) | D6: Road | E6: =SUMIF('Sales Data'!F2:F222,D6,'Sales Data'!I2:I222)
A7: Units Sold | B7: =SUM('Sales Data'!G2:G222) | D7: City | E7: =SUMIF('Sales Data'!F2:F222,D7,'Sales Data'!I2:I222)
A8: Profit Margin % | B8: =SUM('Sales Data'!L2:L222)/SUM('Sales Data'!I2:I222) | D8: Electric | E8: =SUMIF('Sales Data'!F2:F222,D8,'Sales Data'!I2:I222)
D9: Kids | E9: =SUMIF('Sales Data'!F2:F222,D9,'Sales Data'!I2:I222)
D10: BMX | E10: =SUMIF('Sales Data'!F2:F222,D10,'Sales Data'!I2:I222)
A12: REVENUE BY REGION | D12: REVENUE BY SALESPERSON
A13: Region | B13: Revenue | D13: Salesperson | E13: Revenue
A14: North | B14: =SUMIF('Sales Data'!C2:C222,A14,'Sales Data'!I2:I222) | D14: Alice Johnson | E14: =SUMIF('Sales Data'!D2:D222,D14,'Sales Data'!I2:I222)
A15: South | B15: =SUMIF('Sales Data'!C2:C222,A15,'Sales Data'!I2:I222) | D15: Bob Smith | E15: =SUMIF('Sales Data'!D2:D222,D15,'Sales Data'!I2:I222)
A16: East | B16: =SUMIF('Sales Data'!C2:C222,A16,'Sales Data'!I2:I222) | D16: Carol White | E16: =SUMIF('Sales Data'!D2:D222,D16,'Sales Data'!I2:I222)
A17: West | B17: =SUMIF('Sales Data'!C2:C222,A17,'Sales Data'!I2:I222) | D17: David Brown | E17: =SUMIF('Sales Data'!D2:D222,D17,'Sales Data'!I2:I222)
D18: Eve Davis | E18: =SUMIF('Sales Data'!D2:D222,D18,'Sales Data'!I2:I222)
